marmot/__init__.py
marmot/ensemble_model.py
marmot/preprocess.py
marmot/single_model.py
marmot/util.py
marmot-0.1.4.dist-info/LICENSE
marmot-0.1.4.dist-info/WHEEL
marmot-0.1.4.dist-info/METADATA
marmot-0.1.4.dist-info/RECORD
